PyPasta/__init__.py
PyPasta/main.py
PyPasta-0.1.dist-info/LICENSE
PyPasta-0.1.dist-info/METADATA
PyPasta-0.1.dist-info/WHEEL
PyPasta-0.1.dist-info/top_level.txt
PyPasta-0.1.dist-info/RECORD
