Metadata-Version: 2.1
Name: PyPasta
Version: 0.1
Summary: Upload and retrieve pastes from Pastebin via Python EASLY .
Home-page: https://github.com/DevZ44d/PyPasta
Author: Deep
Author-email: asyncpy@proton.me
License: MIT
Classifier: Programming Language :: Python :: 3
Classifier: License :: OSI Approved :: MIT License
Classifier: Operating System :: OS Independent
Requires-Python: >=3.6
License-File: LICENSE
